aiorestlight/__init__.py
aiorestlight/exceptions.py
aiorestlight/restlight.py
aiorestlight/typing.py
aiorestlight-0.1.1.dist-info/LICENSE
aiorestlight-0.1.1.dist-info/METADATA
aiorestlight-0.1.1.dist-info/WHEEL
aiorestlight-0.1.1.dist-info/top_level.txt
aiorestlight-0.1.1.dist-info/RECORD
